tux_gpt/__init__.py
tux_gpt/tux_gpt.py
tux_gpt-0.2.8.dist-info/licenses/LICENSE
tux_gpt-0.2.8.dist-info/METADATA
tux_gpt-0.2.8.dist-info/WHEEL
tux_gpt-0.2.8.dist-info/entry_points.txt
tux_gpt-0.2.8.dist-info/top_level.txt
tux_gpt-0.2.8.dist-info/RECORD
