Metadata-Version: 2.4
Name: tux-gpt
Version: 0.2.8
Summary: An interactive terminal tool using GPT, with web search capabilities.
Author: Fábio Berbert de Paula
Requires-Python: >=3.7
License-File: LICENSE
Requires-Dist: openai>=0.27.0
Requires-Dist: prompt-toolkit>=3.0.0
Requires-Dist: rich>=10.0.0
Requires-Dist: importlib-metadata>=4.0; python_version < "3.8"
Provides-Extra: dev
Requires-Dist: pytest; extra == "dev"
Requires-Dist: mypy; extra == "dev"
Requires-Dist: flake8; extra == "dev"
Dynamic: author
Dynamic: description
Dynamic: description-content-type
Dynamic: license-file
Dynamic: provides-extra
Dynamic: requires-dist
Dynamic: requires-python
Dynamic: summary
